camset/__init__.py
camset/cam_window.py
camset/camset.py
camset/dialogs.py
camset/helpers.py
camset/layout.py
camset/test_gstream.py
camset/toolbar.py
camset/v4l2.py
camset/v4l2control.py
camset/lib/__init__.py
camset/lib/cam_window.py
camset/lib/dialogs.py
camset/lib/helpers.py
camset/lib/layout.py
camset/lib/v4l2control.py
camset/packages/__init__.py
camset/packages/cam_window.py
camset/packages/dialogs.py
camset/packages/helpers.py
camset/packages/layout.py
camset/packages/v4l2control.py
camset-0.0.21.data/data/share/applications/camset.desktop
camset-0.0.21.data/data/share/icons/camset.png
camset-0.0.21.dist-info/LICENSE
camset-0.0.21.dist-info/METADATA
camset-0.0.21.dist-info/WHEEL
camset-0.0.21.dist-info/entry_points.txt
camset-0.0.21.dist-info/top_level.txt
camset-0.0.21.dist-info/RECORD
