Metadata-Version: 2.1
Name: camset
Version: 0.0.21
Summary: GUI for v4l2-ctl
Home-page: https://github.com/azeam/camset
Author: Dennis Hägg
License: UNKNOWN
Platform: UNKNOWN
Classifier: Programming Language :: Python :: 3
Classifier: License :: OSI Approved :: GNU General Public License v3 (GPLv3)
Classifier: Operating System :: POSIX
Requires-Python: >=3.0, <4
License-File: LICENSE
Requires-Dist: PyGObject
Requires-Dist: opencv-python
